[{"stop_id": "3746482927", "stop_name": "Cajueiro Seco", "stop_lat": "-8.1684154", "stop_lon": "-34.9340579"}, {"stop_id": "1551255017", "stop_name": "Prazeres", "stop_lat": "-8.1611341", "stop_lon": "-34.9267437"}, {"stop_id": "1551255016", "stop_name": "Monte dos Guararapes", "stop_lat": "-8.1544942", "stop_lon": "-34.9201550"}, {"stop_id": "1551287912", "stop_name": "Porta Larga", "stop_lat": "-8.1470688", "stop_lon": "-34.9175502"}, {"stop_id": "1428485867", "stop_name": "Aeroporto", "stop_lat": "-8.1341765", "stop_lon": "-34.9146062"}, {"stop_id": "5280081377", "stop_name": "Tancredo Neves", "stop_lat": "-8.1222887", "stop_lon": "-34.9118664"}, {"stop_id": "1428483993", "stop_name": "Shopping", "stop_lat": "-8.1162076", "stop_lon": "-34.9105158"}, {"stop_id": "5280081381", "stop_name": "Ant\u00f4nio Falc\u00e3o", "stop_lat": "-8.1098959", "stop_lon": "-34.9090395"}, {"stop_id": "3600812355", "stop_name": "Imbiribeira", "stop_lat": "-8.0901904", "stop_lon": "-34.9075030"}, {"stop_id": "5280081385", "stop_name": "Largo da Paz", "stop_lat": "-8.0815729", "stop_lon": "-34.9049118"}, {"stop_id": "5279929243", "stop_name": "Joana Bezerra", "stop_lat": "-8.0733039", "stop_lon": "-34.8953654"}, {"stop_id": "5280081387", "stop_name": "Recife", "stop_lat": "-8.0692442", "stop_lon": "-34.8852618"}, {"stop_id": "5280081388", "stop_name": "Recife", "stop_lat": "-8.0691952", "stop_lon": "-34.8853246"}, {"stop_id": "5279929244", "stop_name": "Joana Bezerra", "stop_lat": "-8.0732603", "stop_lon": "-34.8953740"}, {"stop_id": "5280081386", "stop_name": "Largo da Paz", "stop_lat": "-8.0815144", "stop_lon": "-34.9049952"}, {"stop_id": "5280081383", "stop_name": "Imbiribeira", "stop_lat": "-8.0902197", "stop_lon": "-34.9075779"}, {"stop_id": "5280081382", "stop_name": "Ant\u00f4nio Falc\u00e3o", "stop_lat": "-8.1098814", "stop_lon": "-34.9091285"}, {"stop_id": "5280081372", "stop_name": "Shopping", "stop_lat": "-8.1161963", "stop_lon": "-34.9106033"}, {"stop_id": "5280081376", "stop_name": "Tancredo Neves", "stop_lat": "-8.1223060", "stop_lon": "-34.9119145"}, {"stop_id": "5280081374", "stop_name": "Aeroporto", "stop_lat": "-8.1341688", "stop_lon": "-34.9147098"}, {"stop_id": "3741592962", "stop_name": "Porta Larga", "stop_lat": "-8.1469782", "stop_lon": "-34.9176079"}, {"stop_id": "3741592949", "stop_name": "Monte dos Guararapes", "stop_lat": "-8.1544762", "stop_lon": "-34.9202154"}, {"stop_id": "5280081369", "stop_name": "Prazeres", "stop_lat": "-8.1610690", "stop_lon": "-34.9268033"}, {"stop_id": "3746482928", "stop_name": "Cajueiro Seco", "stop_lat": "-8.1683822", "stop_lon": "-34.9340995"}]